hackytools/__init__.py
hackytools/bork.py
hackytools/cli.py
hackytools/gifit.py
hackytools/network_monitor.py
hackytools/sliceit.py
hackytools/spriteit.py
hackytools/utils.py
hackytools-0.2.1.dist-info/LICENSE.txt
hackytools-0.2.1.dist-info/METADATA
hackytools-0.2.1.dist-info/WHEEL
hackytools-0.2.1.dist-info/entry_points.txt
hackytools-0.2.1.dist-info/top_level.txt
hackytools-0.2.1.dist-info/RECORD
