Metadata-Version: 2.1
Name: hackytools
Version: 0.2.1
Summary: Tools that are hacky. Obviously.
Home-page: https://github.com/H4CKY54CK/hackytools
Author: Hackysack
Author-email: tk13xr37@gmail.com
License: MIT License
Platform: UNKNOWN
Requires-Python: >=3.6
Requires-Dist: speedtest-cli
Requires-Dist: pillow (<=8.0.1)
